pygame3d/__init__.py
pygame3d/camera.py
pygame3d/entity.py
pygame3d/light.py
pygame3d/mesh.py
pygame3d/surface3d.py
pygame3d-0.1.1.dist-info/licenses/LICENSE
pygame3d-0.1.1.dist-info/METADATA
pygame3d-0.1.1.dist-info/WHEEL
pygame3d-0.1.1.dist-info/top_level.txt
pygame3d-0.1.1.dist-info/RECORD
