Metadata-Version: 2.4
Name: pygame3d
Version: 0.1.1
Summary: A library for 3D rendering in PyGame
Home-page: https://github.com/Fr5ctal-Projects/pygame3d
Author: Fr5ctal
Author-email: fr5ctal@gmail.com
License: MIT
Classifier: Programming Language :: Python :: 3
Classifier: License :: OSI Approved :: MIT License
Classifier: Operating System :: OS Independent
Requires-Python: >=3.7
License-File: LICENSE
Requires-Dist: panda3d>=1.10.15
Requires-Dist: panda3d-gltf>=1.2.1
Requires-Dist: pygame>=2.0.0
Dynamic: author
Dynamic: author-email
Dynamic: classifier
Dynamic: description
Dynamic: description-content-type
Dynamic: home-page
Dynamic: license
Dynamic: license-file
Dynamic: requires-dist
Dynamic: requires-python
Dynamic: summary
